{"version":1,"resource":"file:///home/lr/Projects/WeDrink/shooza-app-frontend/.gitignore","entries":[{"id":"ySrJ","timestamp":1692739116595},{"id":"507s","source":"undoRedo.source","timestamp":1692739164704},{"id":"XV1F","timestamp":1692739609311},{"id":"eXm3","timestamp":1692739651255},{"id":"mvHt","timestamp":1692739678570},{"id":"JgL8","timestamp":1692739720534},{"id":"Dgdt","timestamp":1692739767449},{"id":"Mi1k","timestamp":1692745222712},{"id":"x04o","source":"undoRedo.source","timestamp":1692745224952},{"id":"yMec","timestamp":1692747356370},{"id":"LfCc","source":"undoRedo.source","timestamp":1692747362534},{"id":"Woeq","timestamp":1693015331770},{"id":"kYXe","source":"undoRedo.source","timestamp":1693015511173}]}