{"version":1,"resource":"file:///home/lr/Projects/personal/portfolio2/src/scss/base/_resets.scss","entries":[{"id":"mYTu.scss","timestamp":1668403917504},{"id":"v2eu.scss","timestamp":1668404013724},{"id":"2HJ0.scss","timestamp":1668437401870},{"id":"X0Ue.scss","timestamp":1668437739658},{"id":"vFiJ.scss","timestamp":1668437895650},{"id":"FDXZ.scss","timestamp":1668437929470},{"id":"HE1E.scss","timestamp":1668437941330},{"id":"7xVt.scss","timestamp":1668437972438},{"id":"LBAN.scss","timestamp":1668437982678},{"id":"U5h7.scss","timestamp":1668438040406},{"id":"9FgT.scss","timestamp":1668438055874},{"id":"RteG.scss","timestamp":1668438121058},{"id":"6RZe.scss","timestamp":1668438153990},{"id":"ATE2.scss","timestamp":1668438186530},{"id":"buRX.scss","timestamp":1668438198782},{"id":"1a4f.scss","timestamp":1668438220906}]}