{"version":1,"resource":"file:///home/lr/Projects/bizarrap-web/dashboard.bizarrap/src/pages/Login/Login.tsx","entries":[{"id":"yEGv.tsx","timestamp":1689870594537},{"id":"AESJ.tsx","timestamp":1689874325334},{"id":"VQuj.tsx","timestamp":1689874531529},{"id":"g9Sc.tsx","timestamp":1689874699241},{"id":"tBCC.tsx","timestamp":1689874796477},{"id":"QlCq.tsx","timestamp":1689874899461},{"id":"ykCx.tsx","timestamp":1689874983433},{"id":"Dj9M.tsx","timestamp":1689875000837},{"id":"dkuO.tsx","timestamp":1689875039549},{"id":"YZQE.tsx","timestamp":1689875255641},{"id":"sKqz.tsx","timestamp":1689875907301},{"id":"4OEg.tsx","timestamp":1689875923689},{"id":"QkXV.tsx","timestamp":1689875943313},{"id":"9j0x.tsx","timestamp":1689876056305},{"id":"85VR.tsx","timestamp":1689888115132},{"id":"iVM4.tsx","timestamp":1689888342036},{"id":"Sbxh.tsx","timestamp":1689888446876},{"id":"CG6u.tsx","timestamp":1689889112083},{"id":"oJnG.tsx","timestamp":1689889507155},{"id":"l0yW.tsx","source":"undoRedo.source","timestamp":1689890141977},{"id":"1f30.tsx","timestamp":1689890211671},{"id":"1a2G.tsx","timestamp":1689890230891},{"id":"wuu1.tsx","timestamp":1689890343213},{"id":"3wi8.tsx","source":"undoRedo.source","timestamp":1689890729974},{"id":"qLTq.tsx","timestamp":1689890785558},{"id":"sRK8.tsx","timestamp":1689890982626},{"id":"oibA.tsx","timestamp":1689891024498},{"id":"P9up.tsx","timestamp":1689891199351},{"id":"r5kw.tsx","timestamp":1691596795583},{"id":"1MWJ.tsx","source":"undoRedo.source","timestamp":1691596805502},{"id":"Fibc.tsx","timestamp":1695411274580},{"id":"O9lc.tsx","timestamp":1695411303980},{"id":"q9ts.tsx","timestamp":1695649241275},{"id":"RVlT.tsx","timestamp":1695649272731},{"id":"Rlea.tsx","timestamp":1695755559844},{"id":"SqqR.tsx","timestamp":1695755772596},{"id":"TpZU.tsx","timestamp":1695755863006},{"id":"3kR9.tsx","timestamp":1695755921780},{"id":"2WC5.tsx","timestamp":1695755935144},{"id":"mO6q.tsx","timestamp":1695755957079},{"id":"oFug.tsx","timestamp":1695755973735},{"id":"ooP0.tsx","timestamp":1695756030086},{"id":"7jOZ.tsx","timestamp":1695756761561},{"id":"vd7v.tsx","timestamp":1695756851477},{"id":"gxyi.tsx","timestamp":1695756955368},{"id":"2cJF.tsx","timestamp":1695756968828},{"id":"C0gu.tsx","timestamp":1695756986996},{"id":"WlRV.tsx","timestamp":1695824120799},{"id":"lqtE.tsx","timestamp":1695824328082},{"id":"apW0.tsx","timestamp":1695924226435}]}