{"version":1,"resource":"file:///home/lr/Projects/WeDrink/wedrink-frontend/src/redux/slices/global/user.js","entries":[{"id":"zCte.js","timestamp":1665264600016},{"id":"7GSG.js","timestamp":1665264778535},{"id":"EkVT.js","timestamp":1665350377013},{"id":"rwAP.js","timestamp":1665350437808},{"id":"5yYJ.js","timestamp":1665350476060},{"id":"FO6P.js","timestamp":1665418376967},{"id":"OyTA.js","timestamp":1665418399132},{"id":"3mHI.js","timestamp":1665418776592},{"id":"kFYD.js","timestamp":1665418917071},{"id":"TD7U.js","timestamp":1665418937691},{"id":"4C0S.js","timestamp":1665514794668},{"id":"TGky.js","source":"undoRedo.source","timestamp":1665515119511},{"id":"UCt8.js","timestamp":1665515245627},{"id":"5CgI.js","source":"undoRedo.source","timestamp":1665515481660},{"id":"HZWe.js","source":"undoRedo.source","timestamp":1665515945249},{"id":"uuEg.js","timestamp":1665516569472},{"id":"E8E9.js","timestamp":1665691360669},{"id":"NS7F.js","timestamp":1665691396041},{"id":"D4IW.js","timestamp":1665693925013},{"id":"k26p.js","timestamp":1665694108872},{"id":"8vLH.js","timestamp":1665694198912},{"id":"fyaA.js","timestamp":1665694524932},{"id":"V6AJ.js","timestamp":1665694859805},{"id":"K4Ar.js","timestamp":1665694901993},{"id":"GgN0.js","timestamp":1665694995923},{"id":"BMi1.js","timestamp":1665847040425},{"id":"LFIq.js","timestamp":1666627198011},{"id":"ENRg.js","timestamp":1666627446772},{"id":"A77u.js","timestamp":1666907351111},{"id":"QVpo.js","timestamp":1666908380129},{"id":"cFsD.js","timestamp":1666980162303},{"id":"CEOe.js","timestamp":1667082760891},{"id":"PmBi.js","timestamp":1667082785051},{"id":"YqBu.js","timestamp":1667082877920},{"id":"xsxp.js","timestamp":1667083030123},{"id":"FgU9.js","timestamp":1667083244776},{"id":"4j4C.js","timestamp":1686343109866},{"id":"V0IK.js","timestamp":1686344332349},{"id":"eDSX.js","timestamp":1686344433736},{"id":"cwom.js","timestamp":1686344482075},{"id":"GjjH.js","timestamp":1686344511583},{"id":"frXt.js","timestamp":1686344535995},{"id":"l2Ld.js","timestamp":1686344649190},{"id":"LQ48.js","timestamp":1686344663569},{"id":"waT5.js","timestamp":1686344727137},{"id":"oAnx.js","timestamp":1686344825888},{"id":"04NK.js","timestamp":1686344971554},{"id":"Ffjq.js","timestamp":1690400565523},{"id":"1jhk.js","source":"undoRedo.source","timestamp":1690400622731},{"id":"V4EA.js","timestamp":1691633060231}]}