{"version":1,"resource":"file:///home/lr/Projects/WeDrink/wedrink-frontend/src/pages/owner-manager/Statistics/Statistics.jsx","entries":[{"id":"1cCJ.jsx","timestamp":1660252178490},{"id":"kp2g.jsx","timestamp":1660252878814},{"id":"oK2j.jsx","timestamp":1660252897170},{"id":"CCoz.jsx","timestamp":1660253107695},{"id":"JgKk.jsx","source":"moved.source","timestamp":1660254514741},{"id":"sLiU.jsx","source":"moved.source","timestamp":1660254546831},{"id":"63dQ.jsx","source":"Workspace Edit","timestamp":1660329590325},{"id":"ttjG.jsx","source":"searchReplace.source","timestamp":1660339306735},{"id":"L04D.jsx","source":"searchReplace.source","timestamp":1660349695105},{"id":"dLyr.jsx","source":"searchReplace.source","timestamp":1660353805726},{"id":"1J4I.jsx","source":"searchReplace.source","timestamp":1660354177277},{"id":"hULZ.jsx","timestamp":1663238148585},{"id":"jkLX.jsx","source":"undoRedo.source","timestamp":1663238167755},{"id":"bfA5.jsx","timestamp":1663239947079},{"id":"Z8mR.jsx","source":"undoRedo.source","timestamp":1663240390775},{"id":"yXb9.jsx","timestamp":1663240781116},{"id":"Crvh.jsx","timestamp":1666309746312},{"id":"vggb.jsx","timestamp":1666309756929},{"id":"ynxL.jsx","source":"undoRedo.source","timestamp":1666309954397},{"id":"uNvv.jsx","timestamp":1666714238940},{"id":"9J1F.jsx","timestamp":1666714277153},{"id":"6289.jsx","timestamp":1685489237035},{"id":"Xwae.jsx","timestamp":1685491110670},{"id":"8Z79.jsx","timestamp":1685491162738},{"id":"dOG5.jsx","source":"Workspace Edit","timestamp":1685491168426},{"id":"yBOf.jsx","timestamp":1685491367692},{"id":"JQOh.jsx","timestamp":1685491414224},{"id":"BvFN.jsx","timestamp":1687264803095},{"id":"oSRL.jsx","timestamp":1687268661409},{"id":"f15h.jsx","timestamp":1687898571187},{"id":"zcCZ.jsx","timestamp":1690056287612},{"id":"isMz.jsx","timestamp":1690061404008},{"id":"WOfU.jsx","source":"Workspace Edit","timestamp":1690061409756},{"id":"t3eP.jsx","timestamp":1690061416404},{"id":"c7nJ.jsx","timestamp":1690061472020},{"id":"IPne.jsx","timestamp":1690061605112},{"id":"vIH3.jsx","timestamp":1691517416948},{"id":"1T0S.jsx","timestamp":1691517460496},{"id":"asGt.jsx","timestamp":1691517501740},{"id":"w7K1.jsx","timestamp":1691517697798},{"id":"lbcf.jsx","timestamp":1691630697821},{"id":"Ddeo.jsx","timestamp":1691631075095},{"id":"gKXr.jsx","timestamp":1691631102607},{"id":"DQML.jsx","timestamp":1691631123136},{"id":"X3Gl.jsx","timestamp":1691631136564},{"id":"VXok.jsx","timestamp":1691631153181},{"id":"89rw.jsx","timestamp":1691631524352},{"id":"AxJL.jsx","timestamp":1691631543004}]}