{"version":1,"resource":"file:///home/lr/Projects/WeDrink/wedrink-frontend/src/pages/owner-manager/SettingsSelection/Roles/Roles.jsx","entries":[{"id":"KopW.jsx","timestamp":1660332287169},{"id":"DtYx.jsx","source":"moved.source","timestamp":1660336352194},{"id":"wj7c.jsx","source":"moved.source","timestamp":1660336415066},{"id":"gP6F.jsx","source":"searchReplace.source","timestamp":1660354177633},{"id":"Lkk0.jsx","timestamp":1660594398679},{"id":"dT1Q.jsx","timestamp":1663344676510},{"id":"THg2.jsx","timestamp":1663425451849},{"id":"bBAV.jsx","timestamp":1663425580905},{"id":"SnuE.jsx","timestamp":1663425832727},{"id":"6bXj.jsx","timestamp":1663425987560},{"id":"G0Os.jsx","timestamp":1663426827302}]}