{"version":1,"resource":"file:///home/lr/Projects/WeDrink/nuvo/wedrink-frontend/src/pages/Organizer/Statistics/PDF/PDFDocument.js","entries":[{"id":"TGHV.jsx","source":"undoRedo.source","timestamp":1654711919569},{"id":"OeNb.jsx","timestamp":1654712388618},{"id":"wGsr.jsx","timestamp":1654712399661},{"id":"yFte.jsx","timestamp":1654712964091},{"id":"FUwk.jsx","source":"undoRedo.source","timestamp":1654712987776},{"id":"xp64.jsx","timestamp":1654799932609},{"id":"3c4c.jsx","timestamp":1654800079729},{"id":"zxBM.jsx","timestamp":1654800098978},{"id":"4usg.jsx","timestamp":1654802485405},{"id":"AmeR.jsx","timestamp":1654802840012},{"id":"QsIn.jsx","timestamp":1654803078214},{"id":"gysj.jsx","timestamp":1654803091418},{"id":"1XjJ.jsx","timestamp":1654803261953},{"id":"7VpZ.jsx","timestamp":1654804799751},{"id":"DO0A.js","timestamp":1654805478589},{"id":"Y20e.js","timestamp":1654805488461},{"id":"b9Cb.js","timestamp":1654805580278},{"id":"sryE.js","timestamp":1654806089486},{"id":"KGLR.js","timestamp":1654810593139},{"id":"UmvU.js","timestamp":1654810765773},{"id":"dVzB.js","timestamp":1654810852665},{"id":"1WJ3.jsx","source":"renamed.source","timestamp":1654810885494},{"id":"7bjF.js","source":"renamed.source","timestamp":1654810927719},{"id":"ZRko.js","source":"moved.source","timestamp":1654810928982},{"id":"OUSj.js","source":"moved.source","timestamp":1654811007085}]}