{"version":1,"resource":"file:///home/lr/Projects/WeDrink/shooza-app-frontend/src/components/partyUser/OrderCard/OrderCard.jsx","entries":[{"id":"QYBE.jsx","timestamp":1694126228810},{"id":"goiK.jsx","timestamp":1694126273898},{"id":"mKQu.jsx","source":"undoRedo.source","timestamp":1694126366193},{"id":"k8Jj.jsx","timestamp":1697686156460},{"id":"W1y3.jsx","timestamp":1697686183528},{"id":"Vgwd.jsx","timestamp":1697686241356},{"id":"O983.jsx","timestamp":1697686259040},{"id":"W4cH.jsx","timestamp":1697686478870},{"id":"aBym.jsx","source":"undoRedo.source","timestamp":1697686498818},{"id":"usPa.jsx","timestamp":1697687327777},{"id":"6rTk.jsx","timestamp":1697687347380},{"id":"g4Ei.jsx","timestamp":1697687378260},{"id":"2c3M.jsx","source":"undoRedo.source","timestamp":1697687496026},{"id":"ExPP.jsx","timestamp":1697687637155},{"id":"fWDr.jsx","timestamp":1697687715965},{"id":"vO8E.jsx","timestamp":1697687990266},{"id":"QQkF.jsx","timestamp":1697688193290},{"id":"bv5h.jsx","timestamp":1697726361044},{"id":"rdHO.jsx","source":"undoRedo.source","timestamp":1697729967443}]}