{"version":1,"resource":"file:///home/lr/Projects/WeDrink/wedrink-frontend/src/utils/countries-code.json","entries":[{"id":"dalS.json","timestamp":1662924167223},{"id":"Wpu2.json","timestamp":1662924732287},{"id":"Jqy3.json","timestamp":1662924754180},{"id":"2IlB.json","timestamp":1662924766209},{"id":"olmz.json","timestamp":1662924836188},{"id":"gotb.json","timestamp":1662925252813},{"id":"dFwR.json","timestamp":1662925396678},{"id":"lcD4.json","timestamp":1662926144162},{"id":"XqvH.json","timestamp":1662926216952},{"id":"BNy3.json","timestamp":1662926303371},{"id":"8PvU.json","timestamp":1662926394011},{"id":"xBnu.json","source":"undoRedo.source","timestamp":1662926416803},{"id":"xikm.json","timestamp":1663002362774},{"id":"UxaN.json","timestamp":1663003002944},{"id":"coxn.json","timestamp":1663012367085},{"id":"GzKC.json","timestamp":1663012410705},{"id":"TjKy.json","timestamp":1663012476809},{"id":"s8Cl.json","timestamp":1663012556116},{"id":"KQtJ.json","timestamp":1663012615504}]}