{"version":1,"resource":"file:///home/lr/Projects/WeDrink/wedrink-frontend/src/components/BackButton/BackButton.jsx","entries":[{"id":"UTYB.jsx","timestamp":1652715152503},{"id":"5ztt.jsx","timestamp":1653055221454},{"id":"IWof.jsx","timestamp":1653055306158},{"id":"xlwq.jsx","timestamp":1653055324210},{"id":"NkBf.jsx","timestamp":1653055363366},{"id":"ytPn.jsx","source":"undoRedo.source","timestamp":1653055770608},{"id":"uso5.jsx","timestamp":1653510145067},{"id":"Ievg.jsx","timestamp":1653510158335}]}