{"version":1,"resource":"file:///home/lr/Projects/WeDrink/shooza-app-frontend/src/pages/partyUser/Checkout/DeliveryMethods/delivery-methods.scss","entries":[{"id":"xZXZ.scss","timestamp":1696556270020},{"id":"6Sjr.scss","timestamp":1696556317303},{"id":"deoh.scss","timestamp":1696557072016},{"id":"TsP8.scss","timestamp":1696557132778},{"id":"Ziv1.scss","timestamp":1696557175188},{"id":"m37q.scss","timestamp":1696557193345},{"id":"BUHg.scss","source":"undoRedo.source","timestamp":1696557215370},{"id":"e2xI.scss","timestamp":1696557261252},{"id":"dc3S.scss","source":"undoRedo.source","timestamp":1696557279028},{"id":"dcVg.scss","timestamp":1696557287593},{"id":"dhRN.scss","timestamp":1696557485374},{"id":"vCTv.scss","timestamp":1696557499478},{"id":"LKna.scss","timestamp":1696557511567},{"id":"RAhQ.scss","timestamp":1696562142026},{"id":"9pKs.scss","source":"renamed.source","timestamp":1696562219634},{"id":"POkC.scss","source":"moved.source","timestamp":1696562304323},{"id":"MPeE.scss","timestamp":1696563303833},{"id":"eaBB.scss","timestamp":1696563355500},{"id":"VdON.scss","timestamp":1696569730604},{"id":"jjux.scss","timestamp":1696619417585},{"id":"rf0C.scss","timestamp":1696619427892},{"id":"qqnZ.scss","timestamp":1696619608611},{"id":"5yIn.scss","timestamp":1696619620879},{"id":"bkam.scss","timestamp":1696619646703},{"id":"YWyZ.scss","timestamp":1696619796918},{"id":"Q4gc.scss","timestamp":1696620195734},{"id":"R9Kr.scss","source":"undoRedo.source","timestamp":1696620201217},{"id":"MGA0.scss","timestamp":1696620208189},{"id":"TzB4.scss","timestamp":1696620312867},{"id":"KZzx.scss","timestamp":1696620355951},{"id":"q3H7.scss","source":"undoRedo.source","timestamp":1696620359303},{"id":"pgvj.scss","timestamp":1696620558795},{"id":"UcI7.scss","timestamp":1696620582251},{"id":"ZS09.scss","timestamp":1696620657315},{"id":"lNF2.scss","timestamp":1696620670099},{"id":"Rfg7.scss","timestamp":1696620703987},{"id":"YSBr.scss","timestamp":1696620905776},{"id":"qC5k.scss","timestamp":1696620952885},{"id":"OXz6.scss","timestamp":1696621001815},{"id":"XIQj.scss","timestamp":1696621044933}]}