{"version":1,"resource":"file:///home/lr/Projects/WeDrink/nuvo/wedrink-frontend/src/pages/Organizer/Inventory/Item/Item.jsx","entries":[{"id":"pNQe.jsx","timestamp":1656528029889},{"id":"RiSX.jsx","timestamp":1656528323293},{"id":"O73K.jsx","timestamp":1656528435597},{"id":"GwPg.jsx","timestamp":1656528463377},{"id":"DO0w.jsx","timestamp":1656528480641},{"id":"DH3e.jsx","timestamp":1656528512325},{"id":"jEfL.jsx","source":"undoRedo.source","timestamp":1656528559961},{"id":"3Svh.jsx","timestamp":1656528570213},{"id":"ZJ1Z.jsx","timestamp":1656529399137},{"id":"V9pW.jsx","timestamp":1656529437201},{"id":"tU3q.jsx","timestamp":1656529488498},{"id":"xKgR.jsx","timestamp":1656529684137},{"id":"SOjJ.jsx","timestamp":1656530727737},{"id":"lh8u.jsx","timestamp":1656531031761},{"id":"uUA2.jsx","timestamp":1656531073011},{"id":"sGT8.jsx","timestamp":1656531181627},{"id":"lVrt.jsx","timestamp":1656531223281},{"id":"tQGf.jsx","timestamp":1656531606033},{"id":"ozEG.jsx","timestamp":1656531728606},{"id":"cvKg.jsx","timestamp":1656531966698},{"id":"MULZ.jsx","timestamp":1656691185166},{"id":"jcQE.jsx","timestamp":1656691214430},{"id":"e1W5.jsx","timestamp":1656691366108},{"id":"OWXz.jsx","timestamp":1656691379728},{"id":"kZeb.jsx","timestamp":1656691488234},{"id":"Qry2.jsx","timestamp":1656691509414},{"id":"nwpM.jsx","timestamp":1656691527842},{"id":"q27c.jsx","timestamp":1656691540726},{"id":"wH2L.jsx","timestamp":1656692226791},{"id":"X5C6.jsx","timestamp":1656692256023},{"id":"BhVh.jsx","timestamp":1656692284240},{"id":"7EL1.jsx","timestamp":1656692406193},{"id":"ke9J.jsx","timestamp":1656692421437},{"id":"3rrg.jsx","timestamp":1656692663689},{"id":"q9BU.jsx","timestamp":1656692695569},{"id":"f6yF.jsx","timestamp":1656692753574},{"id":"L4Kr.jsx","source":"undoRedo.source","timestamp":1656692760962},{"id":"6fNH.jsx","timestamp":1656692776146},{"id":"vhbS.jsx","timestamp":1656692858999},{"id":"OFlX.jsx","timestamp":1656692899260},{"id":"8qDV.jsx","timestamp":1656692940400},{"id":"zSab.jsx","timestamp":1656700499908},{"id":"Y3OT.jsx","timestamp":1656700521479},{"id":"ybgF.jsx","timestamp":1656700564770},{"id":"s6Mk.jsx","timestamp":1656700597225},{"id":"y8qd.jsx","timestamp":1656700760976},{"id":"zoOY.jsx","timestamp":1656882387226},{"id":"cLuM.jsx","timestamp":1656889887248},{"id":"r4Bg.jsx","timestamp":1656889975190},{"id":"hmh9.jsx","timestamp":1656890080355}]}